COPYING.txt
HACKING.txt
README.txt
ez_setup.py
pylint.rc
setup.py
src/lazr/__init__.py
src/lazr.testing.egg-info/PKG-INFO
src/lazr.testing.egg-info/SOURCES.txt
src/lazr.testing.egg-info/dependency_links.txt
src/lazr.testing.egg-info/namespace_packages.txt
src/lazr.testing.egg-info/not-zip-safe
src/lazr.testing.egg-info/requires.txt
src/lazr.testing.egg-info/top_level.txt
src/lazr/testing/NEWS.txt
src/lazr/testing/README.txt
src/lazr/testing/__init__.py
src/lazr/testing/browser_wrapper.py
src/lazr/testing/jstestdriver.py
src/lazr/testing/version.txt
src/lazr/testing/docs/__init__.py
src/lazr/testing/docs/jstestdriver.txt
src/lazr/testing/tests/__init__.py
src/lazr/testing/tests/jstestdriver.txt
src/lazr/testing/tests/test_docs.py
src/lazr/testing/tests/test_js.py
src/lazr/testing/tests/js/test_error.js
src/lazr/testing/tests/js/test_failure.js
src/lazr/testing/tests/js/test_load.js
src/lazr/testing/tests/js/test_success.js