Metadata-Version: 1.0
Name: lazr.testing
Version: 0.1.2
Summary: A collection of testing helpers.
Home-page: https://launchpad.net/lazr.testing
Author: LAZR Developers
Author-email: lazr-developers@lists.launchpad.net
License: LGPL v3
Download-URL: https://launchpad.net/lazr.testing/+download
Platform: UNKNOWN
Classifier: Development Status :: 5 - Production/Stable
Classifier: Intended Audience :: Developers
Classifier: License :: OSI Approved :: GNU Library or Lesser General Public License (LGPL)
Classifier: Operating System :: OS Independent
Classifier: Programming Language :: Python
